setup.py
vectors.py
vectors/__init__.py
vectors/vectors.py
vectors.egg-info/PKG-INFO
vectors.egg-info/SOURCES.txt
vectors.egg-info/dependency_links.txt
vectors.egg-info/top_level.txt