Metadata-Version: 1.0
Name: vectors
Version: 0.0.7
Summary: A simple vector toolkit dealing with vectors and points         in the 3-dimensional space
Home-page: https://github.com/allelos/vectors
Author: Allelos
Author-email: p.paliagkas@gmail.com
License: The MIT License (MIT)
Platform: UNKNOWN
Classifier: Programming Language :: Python
Classifier: Development Status :: 4 - Beta
Classifier: Topic :: Utilities
Classifier: License :: OSI Approved :: MIT License
